llmgraph/__init__.py
llmgraph/console.py
llmgraph/library/classes.py
llmgraph/library/consts.py
llmgraph/library/engine.py
llmgraph/library/env.py
llmgraph/library/llm.py
llmgraph/library/log.py
llmgraph/library/prompts.py
llmgraph/library/utils.py
llmgraph/library/wikipedia.py
llmgraph/prompts.yaml
llmgraph-1.4.1.dist-info/LICENSE
llmgraph-1.4.1.dist-info/METADATA
llmgraph-1.4.1.dist-info/WHEEL
llmgraph-1.4.1.dist-info/entry_points.txt
llmgraph-1.4.1.dist-info/RECORD
