Metadata-Version: 2.1
Name: llmgraph
Version: 1.4.1
Summary: Create knowledge graphs with LLMs
Home-page: https://github.com/dylanhogg/llmgraph
License: MIT
Keywords: Knowledge graph,LLM
Author: Dylan Hogg
Author-email: dylanhogg@gmail.com
Requires-Python: >=3.11,<4.0
Classifier: Development Status :: 5 - Production/Stable
Classifier: Environment :: Console
Classifier: Intended Audience :: Developers
Classifier: Intended Audience :: Science/Research
Classifier: License :: OSI Approved :: MIT License
Classifier: Programming Language :: Python :: 3
Classifier: Programming Language :: Python :: 3.11
Classifier: Programming Language :: Python :: 3.12
Classifier: Topic :: Scientific/Engineering :: Visualization
Requires-Dist: beautifulsoup4 (>=4.14.2,<5.0.0)
Requires-Dist: click (>=8.3.0,<9.0.0)
Requires-Dist: httpx (>=0.25.0,<0.26.0)
Requires-Dist: joblib (>=1.5.2,<2.0.0)
Requires-Dist: litellm (>=1.77.7,<2.0.0)
Requires-Dist: loguru (>=0.7.2,<0.8.0)
Requires-Dist: matplotlib (>=3.10.7,<4.0.0)
Requires-Dist: networkx (>=3.5,<4.0)
Requires-Dist: omegaconf (>=2.3.0,<3.0.0)
Requires-Dist: python-dotenv (>=1.1.1,<2.0.0)
Requires-Dist: pyvis (>=0.3.2,<0.4.0)
Requires-Dist: rich (>=14.2.0,<15.0.0)
Requires-Dist: tenacity (>=9.1.2,<10.0.0)
Requires-Dist: tqdm (>=4.67.1,<5.0.0)
Requires-Dist: typer (>=0.19.2,<0.20.0)
Project-URL: Repository, https://github.com/dylanhogg/llmgraph
